{
 "Alabama": 15,
        "Alaska": 14,
        "Arizona": 15,
        "Arkansas": 14,
        "California": 15,
        "Colorado": 15,
        "Connecticut": 16,
        "Delaware": 16,
        "District of Columbia": 16,
        "Florida": 15,
        "Georgia": 15,
        "Hawaii": 15,
        "Idaho": 14,
        "Illinois": 15,
        "Indiana": 15,
        "Iowa": 14,
        "Kansas": 14,
        "Kentucky": 16,
        "Louisiana": 15,
        "Maine": 15,
        "Maryland": 15,
        "Massachusetts": 16,
        "Michigan": 14,
        "Minnesota": 15,
        "Mississippi": 15,
        "Missouri": 15,
        "Montana": 14,
        "Nebraska": 15,
        "Nevada": 15,
        "New Hampshire": 15,
        "New Jersey": 16,
        "New Mexico": 15,
        "New York": 16,
        "North Carolina": 15,
        "North Dakota": 14,
        "Ohio": 15,
        "Oklahoma": 15,
        "Oregon": 15,
        "Pennsylvania": 16,
        "Rhode Island": 16,
        "South Carolina": 15,
        "South Dakota": 14,
        "Tennessee": 15,
        "Texas": 15,
        "Utah": 15,
        "Vermont": 15,
        "Virginia": 15,
        "Washington": 15,
        "West Virginia": 15,
        "Wisconsin": 15,
        "Wyoming": 15
}